tsa_lth/__init__.py
tsa_lth/analysis.py
tsa_lth/modelling.py
tsa_lth/tests.py
tsa_lth-0.0.4.dist-info/LICENSE
tsa_lth-0.0.4.dist-info/METADATA
tsa_lth-0.0.4.dist-info/WHEEL
tsa_lth-0.0.4.dist-info/top_level.txt
tsa_lth-0.0.4.dist-info/RECORD
