Metadata-Version: 2.1
Name: tsa-lth
Version: 0.0.4
Summary: Package for time series analysis course on LTH
Author-email: Filipp Lernbo <fi6418le-s@student.lu.se>, Gustaf von Grothusen <gustaf.grothusen@gmail.com>
Project-URL: Homepage, https://github.com/andreasjak/TimeSeriesAnalysis
Project-URL: Bug Tracker, https://github.com/andreasjak/TimeSeriesAnalysis/issues
Classifier: Programming Language :: Python :: 3
Classifier: License :: OSI Approved :: MIT License
Classifier: Operating System :: OS Independent
Requires-Python: >=3.8
License-File: LICENSE
Requires-Dist: filterpy ==1.4.5
Requires-Dist: matplotlib ==3.7.1
Requires-Dist: nfoursid ==1.0.1
Requires-Dist: pandas ==2.1.0
Requires-Dist: scipy ==1.11.0
Requires-Dist: statsmodels ==0.14.0
